zarinpal/__init__.py
zarinpal/errors.py
zarinpal/main.py
zarinpal/models.py
zarinpal-1.0.0.dist-info/LICENSE
zarinpal-1.0.0.dist-info/METADATA
zarinpal-1.0.0.dist-info/WHEEL
zarinpal-1.0.0.dist-info/top_level.txt
zarinpal-1.0.0.dist-info/RECORD
